errudite/__init__.py
errudite/build_blocks/__init__.py
errudite/build_blocks/build_block_detector.py
errudite/build_blocks/definitions.py
errudite/build_blocks/helpers.py
errudite/build_blocks/operators.py
errudite/build_blocks/prim_func.py
errudite/build_blocks/wrapper.py
errudite/build_blocks/prim_funcs/__init__.py
errudite/build_blocks/prim_funcs/apply.py
errudite/build_blocks/prim_funcs/dep_distance.py
errudite/build_blocks/prim_funcs/digits.py
errudite/build_blocks/prim_funcs/freq.py
errudite/build_blocks/prim_funcs/get_meta.py
errudite/build_blocks/prim_funcs/get_prediction.py
errudite/build_blocks/prim_funcs/get_sentence.py
errudite/build_blocks/prim_funcs/is_rewritten_by.py
errudite/build_blocks/prim_funcs/length.py
errudite/build_blocks/prim_funcs/linguistic.py
errudite/build_blocks/prim_funcs/logic_operations.py
errudite/build_blocks/prim_funcs/offset.py
errudite/build_blocks/prim_funcs/overlap.py
errudite/build_blocks/prim_funcs/pattern_parser_operators.py
errudite/build_blocks/prim_funcs/perform.py
errudite/build_blocks/prim_funcs/similar_token.py
errudite/build_blocks/prim_funcs/token.py
errudite/build_blocks/prim_funcs/types.py
errudite/builts/__init__.py
errudite/builts/attribute.py
errudite/builts/built_block.py
errudite/builts/group.py
errudite/builts/task_defaults.py
errudite/builts/helpers/__init__.py
errudite/builts/helpers/create_attrs.py
errudite/builts/helpers/create_groups.py
errudite/builts/helpers/pattern_perform_mapper.py
errudite/download/__init__.py
errudite/download/__main__.py
errudite/io/__init__.py
errudite/io/dataset_reader.py
errudite/io/snli_reader.py
errudite/io/squad_reader.py
errudite/io/sst_reader.py
errudite/predictors/__init__.py
errudite/predictors/predictor.py
errudite/predictors/predictor_allennlp.py
errudite/predictors/nli/__init__.py
errudite/predictors/nli/predictor_decompose_att.py
errudite/predictors/nli/predictor_nli.py
errudite/predictors/qa/__init__.py
errudite/predictors/qa/predictor_bidaf.py
errudite-0.0.3.dist-info/LICENSE
errudite-0.0.3.dist-info/METADATA
errudite-0.0.3.dist-info/WHEEL
errudite-0.0.3.dist-info/top_level.txt
errudite-0.0.3.dist-info/RECORD
