Metadata-Version: 2.1
Name: errudite
Version: 0.0.3
Summary: NLP error analysis.
Home-page: https://github.com/tongshuangwu/
Author: Tongshuang Wu
Author-email: wtshuang@cs.washington.edu
Maintainer: Tongshuang Wu
Maintainer-email: wtshuang@cs.washington.edu
License: BSD 3-Clause License
Platform: Windows
Platform: MacOS
Platform: Unix
Classifier: Development Status :: 2 - Pre-Alpha
Classifier: Intended Audience :: Science/Research
Classifier: Intended Audience :: Developers
Classifier: License :: OSI Approved :: BSD License
Classifier: Natural Language :: English
Classifier: Operating System :: Microsoft :: Windows
Classifier: Operating System :: MacOS
Classifier: Operating System :: Unix
Classifier: Programming Language :: Python
Classifier: Programming Language :: Python :: 3.6
Requires-Dist: altair (==3.0.0)
Requires-Dist: pandas (==0.24.2)
Requires-Dist: overrides (==1.9)
Requires-Dist: tqdm (==4.31.1)
Requires-Dist: dill (==0.2.9)
Requires-Dist: spacy (==2.1.3)
Requires-Dist: pattern (==3.6.0)
Requires-Dist: nltk (==3.4)
Requires-Dist: pyyaml (==5.1.1)
Requires-Dist: flask (==1.0.3)
Requires-Dist: flask-cors (==3.0.8)
